{"ok":true,"brand":"水哥养基","metric":"累计主力净额","unit":"亿元","source":"公开板块分钟资金流","trade_date":"2026-07-15","latest_time":"2026-07-15 14:31","updated_at":"2026-07-15T14:30:44+08:00","refresh_seconds":60,"market":{"code":"live","label":"交易中"},"summary":{"inflow_total":188.46,"outflow_total":-1622.39,"leader":"创新药","leader_value":74.844,"laggard":"国产芯片","laggard_value":-319.9502},"sectors":[{"order":1,"label":"半导体","board_name":"半导体","board_type":"industry","board_type_cn":"行业板块","market":90,"trade_date":"2026-07-15","trade_time":"2026-07-15 14:31","minute":"14:31","value":-264.208,"super_large":-202.7005,"large":-61.5075,"medium":137.824,"small":125.7986,"history":[{"time":"13:52","value":-231.4258},{"time":"13:53","value":-231.7364},{"time":"13:54","value":-231.8442},{"time":"13:55","value":-232.3784},{"time":"13:56","value":-232.2899},{"time":"13:57","value":-232.1879},{"time":"13:58","value":-232.5767},{"time":"13:59","value":-233.0953},{"time":"14:00","value":-234.0746},{"time":"14:01","value":-234.9912},{"time":"14:02","value":-236.5214},{"time":"14:03","value":-237.4725},{"time":"14:04","value":-238.2392},{"time":"14:05","value":-239.1526},{"time":"14:06","value":-240.3015},{"time":"14:07","value":-241.0373},{"time":"14:08","value":-241.825},{"time":"14:09","value":-243.0187},{"time":"14:10","value":-244.1686},{"time":"14:11","value":-245.2476},{"time":"14:12","value":-246.8331},{"time":"14:13","value":-247.4581},{"time":"14:14","value":-248.5017},{"time":"14:15","value":-248.8121},{"time":"14:16","value":-249.1488},{"time":"14:17","value":-249.6539},{"time":"14:18","value":-249.7075},{"time":"14:19","value":-250.1756},{"time":"14:20","value":-250.9494},{"time":"14:21","value":-252.2015},{"time":"14:22","value":-253.7874},{"time":"14:23","value":-255.6206},{"time":"14:24","value":-257.1758},{"time":"14:25","value":-259.3234},{"time":"14:26","value":-260.5528},{"time":"14:27","value":-261.2642},{"time":"14:28","value":-261.629},{"time":"14:29","value":-262.1297},{"time":"14:30","value":-263.0611},{"time":"14:31","value":-264.208}],"stale":false},{"order":2,"label":"存储芯片","board_name":"存储芯片","board_type":"concept","board_type_cn":"概念板块","market":90,"trade_date":"2026-07-15","trade_time":"2026-07-15 14:31","minute":"14:31","value":-246.9149,"super_large":-182.4527,"large":-64.4622,"medium":110.0087,"small":135.7857,"history":[{"time":"13:52","value":-212.6242},{"time":"13:53","value":-212.9736},{"time":"13:54","value":-213.161},{"time":"13:55","value":-213.742},{"time":"13:56","value":-213.7252},{"time":"13:57","value":-213.8522},{"time":"13:58","value":-214.3776},{"time":"13:59","value":-215.0215},{"time":"14:00","value":-216.2171},{"time":"14:01","value":-217.4414},{"time":"14:02","value":-219.015},{"time":"14:03","value":-219.7808},{"time":"14:04","value":-220.3512},{"time":"14:05","value":-221.3169},{"time":"14:06","value":-222.5906},{"time":"14:07","value":-223.3267},{"time":"14:08","value":-224.2501},{"time":"14:09","value":-225.319},{"time":"14:10","value":-226.4885},{"time":"14:11","value":-227.7147},{"time":"14:12","value":-229.4492},{"time":"14:13","value":-230.2455},{"time":"14:14","value":-231.2264},{"time":"14:15","value":-231.5467},{"time":"14:16","value":-231.9302},{"time":"14:17","value":-232.4126},{"time":"14:18","value":-232.4393},{"time":"14:19","value":-232.7444},{"time":"14:20","value":-233.839},{"time":"14:21","value":-235.6133},{"time":"14:22","value":-237.4078},{"time":"14:23","value":-238.9328},{"time":"14:24","value":-240.343},{"time":"14:25","value":-242.4605},{"time":"14:26","value":-243.683},{"time":"14:27","value":-244.0318},{"time":"14:28","value":-244.3666},{"time":"14:29","value":-245.0591},{"time":"14:30","value":-246.0692},{"time":"14:31","value":-246.9149}],"stale":false},{"order":3,"label":"MLCC","board_name":"MLCC","board_type":"concept","board_type_cn":"概念板块","market":90,"trade_date":"2026-07-15","trade_time":"2026-07-15 14:31","minute":"14:31","value":-21.0746,"super_large":-18.6276,"large":-2.447,"medium":3.2715,"small":17.8029,"history":[{"time":"13:52","value":-14.1902},{"time":"13:53","value":-14.3538},{"time":"13:54","value":-14.4618},{"time":"13:55","value":-14.5904},{"time":"13:56","value":-14.6177},{"time":"13:57","value":-14.7009},{"time":"13:58","value":-14.8174},{"time":"13:59","value":-15.2035},{"time":"14:00","value":-15.483},{"time":"14:01","value":-15.6493},{"time":"14:02","value":-15.9348},{"time":"14:03","value":-16.1549},{"time":"14:04","value":-16.3172},{"time":"14:05","value":-16.5601},{"time":"14:06","value":-16.6462},{"time":"14:07","value":-16.8051},{"time":"14:08","value":-16.9843},{"time":"14:09","value":-17.1017},{"time":"14:10","value":-17.7306},{"time":"14:11","value":-18.1346},{"time":"14:12","value":-18.4459},{"time":"14:13","value":-18.57},{"time":"14:14","value":-18.6666},{"time":"14:15","value":-18.7397},{"time":"14:16","value":-18.7984},{"time":"14:17","value":-18.9781},{"time":"14:18","value":-18.9804},{"time":"14:19","value":-19.0258},{"time":"14:20","value":-19.1192},{"time":"14:21","value":-19.4061},{"time":"14:22","value":-19.7804},{"time":"14:23","value":-20.0456},{"time":"14:24","value":-20.2978},{"time":"14:25","value":-20.5718},{"time":"14:26","value":-20.6953},{"time":"14:27","value":-20.7144},{"time":"14:28","value":-20.8124},{"time":"14:29","value":-20.8274},{"time":"14:30","value":-20.9733},{"time":"14:31","value":-21.0746}],"stale":false},{"order":4,"label":"固态电池","board_name":"固态电池","board_type":"concept","board_type_cn":"概念板块","market":90,"trade_date":"2026-07-15","trade_time":"2026-07-15 14:31","minute":"14:31","value":-31.9824,"super_large":-25.6515,"large":-6.3309,"medium":-1.1044,"small":32.7411,"history":[{"time":"13:52","value":-21.8238},{"time":"13:53","value":-22.2104},{"time":"13:54","value":-22.3756},{"time":"13:55","value":-22.6912},{"time":"13:56","value":-22.6242},{"time":"13:57","value":-22.6526},{"time":"13:58","value":-22.7751},{"time":"13:59","value":-22.8988},{"time":"14:00","value":-23.3036},{"time":"14:01","value":-23.6906},{"time":"14:02","value":-24.3839},{"time":"14:03","value":-24.7839},{"time":"14:04","value":-24.9235},{"time":"14:05","value":-25.2962},{"time":"14:06","value":-25.5973},{"time":"14:07","value":-25.8219},{"time":"14:08","value":-26.0934},{"time":"14:09","value":-26.1854},{"time":"14:10","value":-26.6539},{"time":"14:11","value":-27.4689},{"time":"14:12","value":-27.7895},{"time":"14:13","value":-27.9465},{"time":"14:14","value":-28.575},{"time":"14:15","value":-28.6756},{"time":"14:16","value":-28.8109},{"time":"14:17","value":-29.2629},{"time":"14:18","value":-29.2565},{"time":"14:19","value":-29.3303},{"time":"14:20","value":-29.365},{"time":"14:21","value":-29.6533},{"time":"14:22","value":-30.2003},{"time":"14:23","value":-30.7913},{"time":"14:24","value":-30.8658},{"time":"14:25","value":-31.3586},{"time":"14:26","value":-31.5974},{"time":"14:27","value":-31.5531},{"time":"14:28","value":-31.8318},{"time":"14:29","value":-31.7084},{"time":"14:30","value":-31.8687},{"time":"14:31","value":-31.9824}],"stale":false},{"order":5,"label":"锂矿","board_name":"锂矿概念","board_type":"concept","board_type_cn":"概念板块","market":90,"trade_date":"2026-07-15","trade_time":"2026-07-15 14:31","minute":"14:31","value":-10.7759,"super_large":-6.4232,"large":-4.3527,"medium":-4.0968,"small":14.873,"history":[{"time":"13:52","value":-6.6212},{"time":"13:53","value":-6.6787},{"time":"13:54","value":-6.8186},{"time":"13:55","value":-6.9416},{"time":"13:56","value":-6.8693},{"time":"13:57","value":-6.8657},{"time":"13:58","value":-6.9366},{"time":"13:59","value":-7.0704},{"time":"14:00","value":-7.3491},{"time":"14:01","value":-7.7073},{"time":"14:02","value":-8.0218},{"time":"14:03","value":-8.2265},{"time":"14:04","value":-8.3047},{"time":"14:05","value":-8.4373},{"time":"14:06","value":-8.6424},{"time":"14:07","value":-8.8103},{"time":"14:08","value":-8.9784},{"time":"14:09","value":-9.0164},{"time":"14:10","value":-9.2698},{"time":"14:11","value":-9.5634},{"time":"14:12","value":-9.7474},{"time":"14:13","value":-9.8394},{"time":"14:14","value":-10.0436},{"time":"14:15","value":-10.1073},{"time":"14:16","value":-10.1764},{"time":"14:17","value":-10.342},{"time":"14:18","value":-10.356},{"time":"14:19","value":-10.3573},{"time":"14:20","value":-10.3658},{"time":"14:21","value":-10.382},{"time":"14:22","value":-10.5098},{"time":"14:23","value":-10.6084},{"time":"14:24","value":-10.6948},{"time":"14:25","value":-10.7907},{"time":"14:26","value":-10.888},{"time":"14:27","value":-10.9038},{"time":"14:28","value":-10.8816},{"time":"14:29","value":-10.7465},{"time":"14:30","value":-10.7467},{"time":"14:31","value":-10.7759}],"stale":false},{"order":6,"label":"白酒","board_name":"白酒","board_type":"concept","board_type_cn":"概念板块","market":90,"trade_date":"2026-07-15","trade_time":"2026-07-15 14:31","minute":"14:31","value":14.8533,"super_large":6.5386,"large":8.3146,"medium":-8.7817,"small":-6.0712,"history":[{"time":"13:52","value":12.0454},{"time":"13:53","value":12.1325},{"time":"13:54","value":12.1162},{"time":"13:55","value":12.214},{"time":"13:56","value":12.2771},{"time":"13:57","value":12.3697},{"time":"13:58","value":12.3884},{"time":"13:59","value":12.3987},{"time":"14:00","value":12.3848},{"time":"14:01","value":12.5778},{"time":"14:02","value":12.6637},{"time":"14:03","value":12.7595},{"time":"14:04","value":12.8283},{"time":"14:05","value":12.8608},{"time":"14:06","value":12.8913},{"time":"14:07","value":12.9643},{"time":"14:08","value":12.9415},{"time":"14:09","value":13.0287},{"time":"14:10","value":13.1049},{"time":"14:11","value":13.4134},{"time":"14:12","value":13.4796},{"time":"14:13","value":13.5158},{"time":"14:14","value":13.5733},{"time":"14:15","value":13.6136},{"time":"14:16","value":13.612},{"time":"14:17","value":13.6464},{"time":"14:18","value":13.7361},{"time":"14:19","value":13.7645},{"time":"14:20","value":13.8269},{"time":"14:21","value":13.8548},{"time":"14:22","value":13.8846},{"time":"14:23","value":13.9289},{"time":"14:24","value":13.9419},{"time":"14:25","value":13.9319},{"time":"14:26","value":13.9964},{"time":"14:27","value":14.3916},{"time":"14:28","value":14.5534},{"time":"14:29","value":14.6552},{"time":"14:30","value":14.7453},{"time":"14:31","value":14.8533}],"stale":false},{"order":7,"label":"创新药","board_name":"创新药","board_type":"concept","board_type_cn":"概念板块","market":90,"trade_date":"2026-07-15","trade_time":"2026-07-15 14:31","minute":"14:31","value":74.844,"super_large":54.4796,"large":20.3644,"medium":-25.5849,"small":-48.1877,"history":[{"time":"13:52","value":80.6751},{"time":"13:53","value":80.709},{"time":"13:54","value":80.7471},{"time":"13:55","value":80.6904},{"time":"13:56","value":80.5944},{"time":"13:57","value":80.5201},{"time":"13:58","value":80.5315},{"time":"13:59","value":80.6302},{"time":"14:00","value":80.5107},{"time":"14:01","value":80.6032},{"time":"14:02","value":80.62},{"time":"14:03","value":80.4183},{"time":"14:04","value":80.1888},{"time":"14:05","value":80.0038},{"time":"14:06","value":79.6396},{"time":"14:07","value":79.4182},{"time":"14:08","value":79.3381},{"time":"14:09","value":79.0912},{"time":"14:10","value":78.8775},{"time":"14:11","value":78.3778},{"time":"14:12","value":77.8095},{"time":"14:13","value":77.4564},{"time":"14:14","value":77.2789},{"time":"14:15","value":77.0528},{"time":"14:16","value":76.7949},{"time":"14:17","value":76.3283},{"time":"14:18","value":76.0079},{"time":"14:19","value":75.7751},{"time":"14:20","value":75.6341},{"time":"14:21","value":75.5384},{"time":"14:22","value":75.434},{"time":"14:23","value":75.1628},{"time":"14:24","value":74.8342},{"time":"14:25","value":74.6606},{"time":"14:26","value":74.3439},{"time":"14:27","value":74.3387},{"time":"14:28","value":74.4195},{"time":"14:29","value":74.6706},{"time":"14:30","value":74.7271},{"time":"14:31","value":74.844}],"stale":false},{"order":8,"label":"生物疫苗","board_name":"生物疫苗","board_type":"concept","board_type_cn":"概念板块","market":90,"trade_date":"2026-07-15","trade_time":"2026-07-15 14:31","minute":"14:31","value":10.9783,"super_large":9.4621,"large":1.5162,"medium":-5.8596,"small":-5.1134,"history":[{"time":"13:52","value":12.3315},{"time":"13:53","value":12.3241},{"time":"13:54","value":12.3131},{"time":"13:55","value":12.3202},{"time":"13:56","value":12.3298},{"time":"13:57","value":12.2536},{"time":"13:58","value":12.2119},{"time":"13:59","value":12.2076},{"time":"14:00","value":12.1167},{"time":"14:01","value":12.1035},{"time":"14:02","value":12.0874},{"time":"14:03","value":12.0832},{"time":"14:04","value":12.0677},{"time":"14:05","value":12.0314},{"time":"14:06","value":11.9061},{"time":"14:07","value":11.8382},{"time":"14:08","value":11.8414},{"time":"14:09","value":11.8493},{"time":"14:10","value":11.8186},{"time":"14:11","value":11.7202},{"time":"14:12","value":11.6394},{"time":"14:13","value":11.5696},{"time":"14:14","value":11.5141},{"time":"14:15","value":11.4636},{"time":"14:16","value":11.357},{"time":"14:17","value":11.3656},{"time":"14:18","value":11.3309},{"time":"14:19","value":11.3062},{"time":"14:20","value":11.2972},{"time":"14:21","value":11.2487},{"time":"14:22","value":11.2102},{"time":"14:23","value":11.1861},{"time":"14:24","value":11.1493},{"time":"14:25","value":11.083},{"time":"14:26","value":10.9313},{"time":"14:27","value":10.8769},{"time":"14:28","value":10.8869},{"time":"14:29","value":10.9414},{"time":"14:30","value":10.9641},{"time":"14:31","value":10.9783}],"stale":false},{"order":9,"label":"PCB","board_name":"PCB","board_type":"concept","board_type_cn":"概念板块","market":90,"trade_date":"2026-07-15","trade_time":"2026-07-15 14:31","minute":"14:31","value":-69.6643,"super_large":-67.611,"large":-2.0534,"medium":18.39,"small":49.7656,"history":[{"time":"13:52","value":-52.8694},{"time":"13:53","value":-53.0832},{"time":"13:54","value":-53.1898},{"time":"13:55","value":-53.4529},{"time":"13:56","value":-53.327},{"time":"13:57","value":-53.3617},{"time":"13:58","value":-53.6263},{"time":"13:59","value":-54.0224},{"time":"14:00","value":-54.4046},{"time":"14:01","value":-54.9776},{"time":"14:02","value":-55.5869},{"time":"14:03","value":-55.9132},{"time":"14:04","value":-56.073},{"time":"14:05","value":-56.5494},{"time":"14:06","value":-56.7601},{"time":"14:07","value":-57.2997},{"time":"14:08","value":-57.673},{"time":"14:09","value":-58.0297},{"time":"14:10","value":-58.6408},{"time":"14:11","value":-59.4729},{"time":"14:12","value":-60.1879},{"time":"14:13","value":-60.6469},{"time":"14:14","value":-61.1068},{"time":"14:15","value":-61.236},{"time":"14:16","value":-61.3652},{"time":"14:17","value":-61.6238},{"time":"14:18","value":-61.6798},{"time":"14:19","value":-61.8738},{"time":"14:20","value":-62.4342},{"time":"14:21","value":-63.0901},{"time":"14:22","value":-63.9754},{"time":"14:23","value":-65.3577},{"time":"14:24","value":-66.1104},{"time":"14:25","value":-66.9604},{"time":"14:26","value":-67.7868},{"time":"14:27","value":-68.0041},{"time":"14:28","value":-68.3735},{"time":"14:29","value":-68.6776},{"time":"14:30","value":-69.1983},{"time":"14:31","value":-69.6643}],"stale":false},{"order":10,"label":"黄金","board_name":"黄金概念","board_type":"concept","board_type_cn":"概念板块","market":90,"trade_date":"2026-07-15","trade_time":"2026-07-15 14:31","minute":"14:31","value":-8.6231,"super_large":-7.4415,"large":-1.1817,"medium":4.0766,"small":4.5463,"history":[{"time":"13:52","value":-5.6898},{"time":"13:53","value":-5.7326},{"time":"13:54","value":-5.7882},{"time":"13:55","value":-5.6648},{"time":"13:56","value":-5.5508},{"time":"13:57","value":-5.5503},{"time":"13:58","value":-5.6151},{"time":"13:59","value":-5.6831},{"time":"14:00","value":-5.8586},{"time":"14:01","value":-5.944},{"time":"14:02","value":-6.0965},{"time":"14:03","value":-6.1912},{"time":"14:04","value":-6.2078},{"time":"14:05","value":-6.2589},{"time":"14:06","value":-6.3191},{"time":"14:07","value":-6.3646},{"time":"14:08","value":-6.4196},{"time":"14:09","value":-6.432},{"time":"14:10","value":-6.627},{"time":"14:11","value":-6.743},{"time":"14:12","value":-6.799},{"time":"14:13","value":-6.817},{"time":"14:14","value":-6.8585},{"time":"14:15","value":-6.8764},{"time":"14:16","value":-6.85},{"time":"14:17","value":-6.9015},{"time":"14:18","value":-6.8909},{"time":"14:19","value":-6.9623},{"time":"14:20","value":-7.1779},{"time":"14:21","value":-7.4313},{"time":"14:22","value":-7.6586},{"time":"14:23","value":-8.2179},{"time":"14:24","value":-8.3629},{"time":"14:25","value":-8.4255},{"time":"14:26","value":-8.4797},{"time":"14:27","value":-8.4359},{"time":"14:28","value":-8.523},{"time":"14:29","value":-8.5282},{"time":"14:30","value":-8.6326},{"time":"14:31","value":-8.6231}],"stale":false},{"order":11,"label":"CPO","board_name":"CPO概念","board_type":"concept","board_type_cn":"概念板块","market":90,"trade_date":"2026-07-15","trade_time":"2026-07-15 14:31","minute":"14:31","value":-128.1051,"super_large":-104.1138,"large":-23.9913,"medium":10.6237,"small":117.035,"history":[{"time":"13:52","value":-106.4038},{"time":"13:53","value":-106.42},{"time":"13:54","value":-106.4515},{"time":"13:55","value":-106.7846},{"time":"13:56","value":-107.0991},{"time":"13:57","value":-107.2713},{"time":"13:58","value":-107.5715},{"time":"13:59","value":-108.242},{"time":"14:00","value":-108.9534},{"time":"14:01","value":-110.0821},{"time":"14:02","value":-111.1662},{"time":"14:03","value":-111.7101},{"time":"14:04","value":-111.8219},{"time":"14:05","value":-112.2931},{"time":"14:06","value":-112.6585},{"time":"14:07","value":-112.9707},{"time":"14:08","value":-113.1484},{"time":"14:09","value":-113.6458},{"time":"14:10","value":-114.171},{"time":"14:11","value":-115.7262},{"time":"14:12","value":-116.3242},{"time":"14:13","value":-116.7485},{"time":"14:14","value":-117.114},{"time":"14:15","value":-117.256},{"time":"14:16","value":-117.4737},{"time":"14:17","value":-117.7492},{"time":"14:18","value":-117.7167},{"time":"14:19","value":-118.0531},{"time":"14:20","value":-118.824},{"time":"14:21","value":-119.5774},{"time":"14:22","value":-120.4969},{"time":"14:23","value":-122.1441},{"time":"14:24","value":-123.3618},{"time":"14:25","value":-124.6066},{"time":"14:26","value":-125.5949},{"time":"14:27","value":-125.8358},{"time":"14:28","value":-126.12},{"time":"14:29","value":-126.7346},{"time":"14:30","value":-127.2585},{"time":"14:31","value":-128.1051}],"stale":false},{"order":12,"label":"算力","board_name":"算力概念","board_type":"concept","board_type_cn":"概念板块","market":90,"trade_date":"2026-07-15","trade_time":"2026-07-15 14:31","minute":"14:31","value":-70.5649,"super_large":-66.0226,"large":-4.5424,"medium":27.2917,"small":43.0587,"history":[{"time":"13:52","value":-57.4327},{"time":"13:53","value":-57.5062},{"time":"13:54","value":-57.6678},{"time":"13:55","value":-58.021},{"time":"13:56","value":-57.9349},{"time":"13:57","value":-58.0058},{"time":"13:58","value":-58.4532},{"time":"13:59","value":-59.1056},{"time":"14:00","value":-59.6018},{"time":"14:01","value":-59.8285},{"time":"14:02","value":-60.5698},{"time":"14:03","value":-61.0145},{"time":"14:04","value":-61.2402},{"time":"14:05","value":-61.706},{"time":"14:06","value":-61.9893},{"time":"14:07","value":-62.208},{"time":"14:08","value":-62.5107},{"time":"14:09","value":-62.7776},{"time":"14:10","value":-63.2661},{"time":"14:11","value":-63.768},{"time":"14:12","value":-64.0766},{"time":"14:13","value":-64.2191},{"time":"14:14","value":-64.485},{"time":"14:15","value":-64.4442},{"time":"14:16","value":-64.6125},{"time":"14:17","value":-64.8337},{"time":"14:18","value":-64.8181},{"time":"14:19","value":-65.2382},{"time":"14:20","value":-65.4898},{"time":"14:21","value":-66.1645},{"time":"14:22","value":-66.547},{"time":"14:23","value":-67.569},{"time":"14:24","value":-68.3079},{"time":"14:25","value":-68.8563},{"time":"14:26","value":-69.3943},{"time":"14:27","value":-69.334},{"time":"14:28","value":-69.2017},{"time":"14:29","value":-69.3859},{"time":"14:30","value":-69.9231},{"time":"14:31","value":-70.5649}],"stale":false},{"order":13,"label":"液冷","board_name":"液冷概念","board_type":"concept","board_type_cn":"概念板块","market":90,"trade_date":"2026-07-15","trade_time":"2026-07-15 14:31","minute":"14:31","value":-57.1332,"super_large":-42.2219,"large":-14.9113,"medium":5.0687,"small":51.285,"history":[{"time":"13:52","value":-42.9121},{"time":"13:53","value":-42.8453},{"time":"13:54","value":-42.8883},{"time":"13:55","value":-43.2164},{"time":"13:56","value":-43.2633},{"time":"13:57","value":-43.2862},{"time":"13:58","value":-43.6567},{"time":"13:59","value":-44.2155},{"time":"14:00","value":-44.6946},{"time":"14:01","value":-44.9457},{"time":"14:02","value":-45.8902},{"time":"14:03","value":-46.3125},{"time":"14:04","value":-46.304},{"time":"14:05","value":-46.6843},{"time":"14:06","value":-46.7144},{"time":"14:07","value":-47.0867},{"time":"14:08","value":-47.3099},{"time":"14:09","value":-47.5318},{"time":"14:10","value":-47.9796},{"time":"14:11","value":-48.7487},{"time":"14:12","value":-49.2226},{"time":"14:13","value":-49.3976},{"time":"14:14","value":-49.7949},{"time":"14:15","value":-49.7363},{"time":"14:16","value":-49.8093},{"time":"14:17","value":-50.0296},{"time":"14:18","value":-49.9936},{"time":"14:19","value":-50.5031},{"time":"14:20","value":-50.9411},{"time":"14:21","value":-51.6253},{"time":"14:22","value":-52.4139},{"time":"14:23","value":-53.8494},{"time":"14:24","value":-54.7325},{"time":"14:25","value":-55.3661},{"time":"14:26","value":-56.0011},{"time":"14:27","value":-56.1516},{"time":"14:28","value":-56.3103},{"time":"14:29","value":-56.4801},{"time":"14:30","value":-56.9459},{"time":"14:31","value":-57.1332}],"stale":false},{"order":14,"label":"光伏","board_name":"光伏概念","board_type":"concept","board_type_cn":"概念板块","market":90,"trade_date":"2026-07-15","trade_time":"2026-07-15 14:31","minute":"14:31","value":-27.3142,"super_large":-20.5346,"large":-6.7797,"medium":-8.6575,"small":34.5093,"history":[{"time":"13:52","value":-17.3409},{"time":"13:53","value":-17.4722},{"time":"13:54","value":-17.6323},{"time":"13:55","value":-17.8805},{"time":"13:56","value":-17.8642},{"time":"13:57","value":-17.8504},{"time":"13:58","value":-18.0287},{"time":"13:59","value":-18.472},{"time":"14:00","value":-18.8413},{"time":"14:01","value":-19.4719},{"time":"14:02","value":-20.1558},{"time":"14:03","value":-20.452},{"time":"14:04","value":-20.4149},{"time":"14:05","value":-20.9056},{"time":"14:06","value":-21.1519},{"time":"14:07","value":-21.5812},{"time":"14:08","value":-21.6434},{"time":"14:09","value":-22.0483},{"time":"14:10","value":-22.4854},{"time":"14:11","value":-23.1687},{"time":"14:12","value":-23.576},{"time":"14:13","value":-23.6473},{"time":"14:14","value":-23.9122},{"time":"14:15","value":-23.976},{"time":"14:16","value":-24.0378},{"time":"14:17","value":-24.2634},{"time":"14:18","value":-24.129},{"time":"14:19","value":-24.1243},{"time":"14:20","value":-24.5166},{"time":"14:21","value":-25.3184},{"time":"14:22","value":-25.9952},{"time":"14:23","value":-26.526},{"time":"14:24","value":-26.8091},{"time":"14:25","value":-27.1092},{"time":"14:26","value":-27.2132},{"time":"14:27","value":-27.1403},{"time":"14:28","value":-27.3084},{"time":"14:29","value":-27.2223},{"time":"14:30","value":-27.2637},{"time":"14:31","value":-27.3142}],"stale":false},{"order":15,"label":"人形机器人","board_name":"人形机器人","board_type":"concept","board_type_cn":"概念板块","market":90,"trade_date":"2026-07-15","trade_time":"2026-07-15 14:31","minute":"14:31","value":-19.7982,"super_large":-23.3938,"large":3.5955,"medium":13.2724,"small":6.4931,"history":[{"time":"13:52","value":-10.4207},{"time":"13:53","value":-10.5882},{"time":"13:54","value":-10.7113},{"time":"13:55","value":-10.908},{"time":"13:56","value":-10.7238},{"time":"13:57","value":-10.8374},{"time":"13:58","value":-11.0859},{"time":"13:59","value":-11.2742},{"time":"14:00","value":-11.6473},{"time":"14:01","value":-11.7871},{"time":"14:02","value":-12.2613},{"time":"14:03","value":-12.629},{"time":"14:04","value":-12.8427},{"time":"14:05","value":-13.1875},{"time":"14:06","value":-13.4458},{"time":"14:07","value":-13.7543},{"time":"14:08","value":-13.9626},{"time":"14:09","value":-14.6057},{"time":"14:10","value":-15.2471},{"time":"14:11","value":-15.6265},{"time":"14:12","value":-16.5101},{"time":"14:13","value":-16.6793},{"time":"14:14","value":-17.0379},{"time":"14:15","value":-17.0135},{"time":"14:16","value":-16.9752},{"time":"14:17","value":-17.2121},{"time":"14:18","value":-17.0499},{"time":"14:19","value":-17.0591},{"time":"14:20","value":-17.1103},{"time":"14:21","value":-17.3839},{"time":"14:22","value":-18.0631},{"time":"14:23","value":-18.4333},{"time":"14:24","value":-18.589},{"time":"14:25","value":-18.8232},{"time":"14:26","value":-19.2577},{"time":"14:27","value":-19.219},{"time":"14:28","value":-19.3302},{"time":"14:29","value":-19.3245},{"time":"14:30","value":-19.6187},{"time":"14:31","value":-19.7982}],"stale":false},{"order":16,"label":"AI应用","board_name":"AI应用","board_type":"concept","board_type_cn":"概念板块","market":90,"trade_date":"2026-07-15","trade_time":"2026-07-15 14:31","minute":"14:31","value":31.3794,"super_large":22.0451,"large":9.3343,"medium":-15.1673,"small":-16.1393,"history":[{"time":"13:52","value":34.1189},{"time":"13:53","value":34.3504},{"time":"13:54","value":34.4522},{"time":"13:55","value":34.4921},{"time":"13:56","value":34.5351},{"time":"13:57","value":34.4532},{"time":"13:58","value":34.2247},{"time":"13:59","value":33.9441},{"time":"14:00","value":33.766},{"time":"14:01","value":33.9141},{"time":"14:02","value":33.7998},{"time":"14:03","value":33.8595},{"time":"14:04","value":33.8763},{"time":"14:05","value":33.6461},{"time":"14:06","value":33.644},{"time":"14:07","value":33.378},{"time":"14:08","value":33.1473},{"time":"14:09","value":33.106},{"time":"14:10","value":32.9266},{"time":"14:11","value":32.7788},{"time":"14:12","value":32.5977},{"time":"14:13","value":32.5675},{"time":"14:14","value":32.4354},{"time":"14:15","value":32.5242},{"time":"14:16","value":32.5084},{"time":"14:17","value":32.4534},{"time":"14:18","value":32.612},{"time":"14:19","value":32.528},{"time":"14:20","value":32.5342},{"time":"14:21","value":32.255},{"time":"14:22","value":31.9649},{"time":"14:23","value":31.8005},{"time":"14:24","value":31.5491},{"time":"14:25","value":31.4798},{"time":"14:26","value":31.277},{"time":"14:27","value":31.3034},{"time":"14:28","value":31.3676},{"time":"14:29","value":31.3812},{"time":"14:30","value":31.4134},{"time":"14:31","value":31.3794}],"stale":false},{"order":17,"label":"新能源车","board_name":"新能源车","board_type":"concept","board_type_cn":"概念板块","market":90,"trade_date":"2026-07-15","trade_time":"2026-07-15 14:31","minute":"14:31","value":-72.3021,"super_large":-64.3425,"large":-7.9596,"medium":2.7281,"small":68.8763,"history":[{"time":"13:52","value":-45.7422},{"time":"13:53","value":-46.3085},{"time":"13:54","value":-46.6775},{"time":"13:55","value":-47.3491},{"time":"13:56","value":-47.3783},{"time":"13:57","value":-47.5226},{"time":"13:58","value":-47.9441},{"time":"13:59","value":-48.4594},{"time":"14:00","value":-49.4194},{"time":"14:01","value":-50.1358},{"time":"14:02","value":-51.6739},{"time":"14:03","value":-52.3576},{"time":"14:04","value":-52.6148},{"time":"14:05","value":-53.4905},{"time":"14:06","value":-54.0572},{"time":"14:07","value":-54.5653},{"time":"14:08","value":-55.2625},{"time":"14:09","value":-55.5892},{"time":"14:10","value":-56.6406},{"time":"14:11","value":-58.2586},{"time":"14:12","value":-59.67},{"time":"14:13","value":-60.0488},{"time":"14:14","value":-60.8375},{"time":"14:15","value":-61.0431},{"time":"14:16","value":-61.1123},{"time":"14:17","value":-61.4945},{"time":"14:18","value":-61.8203},{"time":"14:19","value":-62.0073},{"time":"14:20","value":-62.4665},{"time":"14:21","value":-63.7842},{"time":"14:22","value":-65.5761},{"time":"14:23","value":-67.1362},{"time":"14:24","value":-68.1257},{"time":"14:25","value":-69.0451},{"time":"14:26","value":-69.9342},{"time":"14:27","value":-70.5145},{"time":"14:28","value":-71.0348},{"time":"14:29","value":-71.2261},{"time":"14:30","value":-71.8416},{"time":"14:31","value":-72.3021}],"stale":false},{"order":18,"label":"商业航天","board_name":"商业航天","board_type":"concept","board_type_cn":"概念板块","market":90,"trade_date":"2026-07-15","trade_time":"2026-07-15 14:31","minute":"14:31","value":-74.5808,"super_large":-45.1967,"large":-29.3842,"medium":12.1179,"small":61.8413,"history":[{"time":"13:52","value":-57.5221},{"time":"13:53","value":-57.8748},{"time":"13:54","value":-58.143},{"time":"13:55","value":-58.4489},{"time":"13:56","value":-58.5221},{"time":"13:57","value":-58.6645},{"time":"13:58","value":-58.9265},{"time":"13:59","value":-59.4933},{"time":"14:00","value":-60.1267},{"time":"14:01","value":-60.347},{"time":"14:02","value":-61.1607},{"time":"14:03","value":-61.6248},{"time":"14:04","value":-61.7599},{"time":"14:05","value":-62.2447},{"time":"14:06","value":-62.6372},{"time":"14:07","value":-63.2875},{"time":"14:08","value":-63.7524},{"time":"14:09","value":-64.0613},{"time":"14:10","value":-64.7489},{"time":"14:11","value":-65.7136},{"time":"14:12","value":-66.3178},{"time":"14:13","value":-66.585},{"time":"14:14","value":-67.3943},{"time":"14:15","value":-67.3866},{"time":"14:16","value":-67.6149},{"time":"14:17","value":-67.9871},{"time":"14:18","value":-67.8886},{"time":"14:19","value":-68.0185},{"time":"14:20","value":-68.208},{"time":"14:21","value":-69.0},{"time":"14:22","value":-69.8695},{"time":"14:23","value":-70.9356},{"time":"14:24","value":-71.7585},{"time":"14:25","value":-72.5454},{"time":"14:26","value":-73.1867},{"time":"14:27","value":-73.308},{"time":"14:28","value":-73.7012},{"time":"14:29","value":-73.8133},{"time":"14:30","value":-74.2548},{"time":"14:31","value":-74.5808}],"stale":false},{"order":19,"label":"银行","board_name":"银行","board_type":"industry","board_type_cn":"行业板块","market":90,"trade_date":"2026-07-15","trade_time":"2026-07-15 14:31","minute":"14:31","value":-18.2294,"super_large":-10.2886,"large":-7.9408,"medium":6.9385,"small":11.2902,"history":[{"time":"13:52","value":-13.9954},{"time":"13:53","value":-14.043},{"time":"13:54","value":-14.1332},{"time":"13:55","value":-14.2907},{"time":"13:56","value":-14.3497},{"time":"13:57","value":-14.407},{"time":"13:58","value":-14.4423},{"time":"13:59","value":-14.5464},{"time":"14:00","value":-14.6398},{"time":"14:01","value":-14.8507},{"time":"14:02","value":-14.9058},{"time":"14:03","value":-14.9707},{"time":"14:04","value":-15.1013},{"time":"14:05","value":-15.2053},{"time":"14:06","value":-15.2433},{"time":"14:07","value":-15.3313},{"time":"14:08","value":-15.5281},{"time":"14:09","value":-15.667},{"time":"14:10","value":-15.7895},{"time":"14:11","value":-15.8803},{"time":"14:12","value":-15.9946},{"time":"14:13","value":-16.1208},{"time":"14:14","value":-16.1928},{"time":"14:15","value":-16.2702},{"time":"14:16","value":-16.3686},{"time":"14:17","value":-16.5268},{"time":"14:18","value":-16.6007},{"time":"14:19","value":-16.7047},{"time":"14:20","value":-16.742},{"time":"14:21","value":-16.8328},{"time":"14:22","value":-16.9835},{"time":"14:23","value":-17.0846},{"time":"14:24","value":-17.1881},{"time":"14:25","value":-17.2687},{"time":"14:26","value":-17.3578},{"time":"14:27","value":-17.6252},{"time":"14:28","value":-17.8589},{"time":"14:29","value":-17.9657},{"time":"14:30","value":-18.0222},{"time":"14:31","value":-18.2294}],"stale":false},{"order":20,"label":"证券","board_name":"证券","board_type":"industry","board_type_cn":"行业板块","market":90,"trade_date":"2026-07-15","trade_time":"2026-07-15 14:31","minute":"14:31","value":30.5731,"super_large":25.6183,"large":4.9548,"medium":-12.1045,"small":-18.4723,"history":[{"time":"13:52","value":29.6783},{"time":"13:53","value":30.4147},{"time":"13:54","value":30.5587},{"time":"13:55","value":30.8197},{"time":"13:56","value":30.8954},{"time":"13:57","value":31.1179},{"time":"13:58","value":31.0936},{"time":"13:59","value":31.1482},{"time":"14:00","value":31.0529},{"time":"14:01","value":31.0836},{"time":"14:02","value":31.2033},{"time":"14:03","value":31.2124},{"time":"14:04","value":31.2283},{"time":"14:05","value":31.2028},{"time":"14:06","value":31.2055},{"time":"14:07","value":31.2117},{"time":"14:08","value":31.2079},{"time":"14:09","value":31.226},{"time":"14:10","value":31.2129},{"time":"14:11","value":31.0992},{"time":"14:12","value":30.9264},{"time":"14:13","value":30.8452},{"time":"14:14","value":30.8175},{"time":"14:15","value":30.812},{"time":"14:16","value":30.7886},{"time":"14:17","value":30.7933},{"time":"14:18","value":30.7876},{"time":"14:19","value":30.7825},{"time":"14:20","value":30.6777},{"time":"14:21","value":30.7146},{"time":"14:22","value":30.6063},{"time":"14:23","value":30.5801},{"time":"14:24","value":30.4961},{"time":"14:25","value":30.3601},{"time":"14:26","value":29.999},{"time":"14:27","value":29.9998},{"time":"14:28","value":30.0478},{"time":"14:29","value":30.3321},{"time":"14:30","value":30.4898},{"time":"14:31","value":30.5731}],"stale":false},{"order":21,"label":"有色金属","board_name":"有色金属","board_type":"industry","board_type_cn":"行业板块","market":90,"trade_date":"2026-07-15","trade_time":"2026-07-15 14:31","minute":"14:31","value":-32.1261,"super_large":-26.4985,"large":-5.6277,"medium":10.7917,"small":21.1861,"history":[{"time":"13:52","value":-24.7786},{"time":"13:53","value":-25.0043},{"time":"13:54","value":-25.083},{"time":"13:55","value":-25.0696},{"time":"13:56","value":-24.8854},{"time":"13:57","value":-24.741},{"time":"13:58","value":-24.8365},{"time":"13:59","value":-24.9523},{"time":"14:00","value":-25.351},{"time":"14:01","value":-25.6136},{"time":"14:02","value":-26.0874},{"time":"14:03","value":-26.4265},{"time":"14:04","value":-26.4992},{"time":"14:05","value":-26.7104},{"time":"14:06","value":-26.8904},{"time":"14:07","value":-27.2145},{"time":"14:08","value":-27.4218},{"time":"14:09","value":-27.5191},{"time":"14:10","value":-27.9271},{"time":"14:11","value":-28.3301},{"time":"14:12","value":-28.5841},{"time":"14:13","value":-28.7789},{"time":"14:14","value":-29.0471},{"time":"14:15","value":-28.9711},{"time":"14:16","value":-29.0121},{"time":"14:17","value":-29.1356},{"time":"14:18","value":-29.1116},{"time":"14:19","value":-29.2773},{"time":"14:20","value":-29.7545},{"time":"14:21","value":-30.1184},{"time":"14:22","value":-30.6374},{"time":"14:23","value":-31.3402},{"time":"14:24","value":-31.5644},{"time":"14:25","value":-31.8484},{"time":"14:26","value":-32.107},{"time":"14:27","value":-31.9355},{"time":"14:28","value":-32.1176},{"time":"14:29","value":-31.9008},{"time":"14:30","value":-32.0442},{"time":"14:31","value":-32.1261}],"stale":false},{"order":22,"label":"细分化工","board_name":"细分化工","board_type":"index","board_type_cn":"指数","market":1,"trade_date":"2026-07-15","trade_time":"2026-07-15 14:31","minute":"14:31","value":-10.0375,"super_large":-5.167,"large":-4.8705,"medium":-1.7064,"small":11.7377,"history":[{"time":"13:52","value":-6.454},{"time":"13:53","value":-6.8184},{"time":"13:54","value":-6.9758},{"time":"13:55","value":-7.0788},{"time":"13:56","value":-7.1101},{"time":"13:57","value":-7.1551},{"time":"13:58","value":-7.2587},{"time":"13:59","value":-7.3666},{"time":"14:00","value":-7.5675},{"time":"14:01","value":-7.6343},{"time":"14:02","value":-7.8416},{"time":"14:03","value":-7.964},{"time":"14:04","value":-8.0609},{"time":"14:05","value":-8.3017},{"time":"14:06","value":-8.2751},{"time":"14:07","value":-8.2817},{"time":"14:08","value":-8.4091},{"time":"14:09","value":-8.4266},{"time":"14:10","value":-8.4459},{"time":"14:11","value":-8.8057},{"time":"14:12","value":-8.8772},{"time":"14:13","value":-8.921},{"time":"14:14","value":-9.0694},{"time":"14:15","value":-9.0998},{"time":"14:16","value":-9.1487},{"time":"14:17","value":-9.1832},{"time":"14:18","value":-9.1954},{"time":"14:19","value":-9.2404},{"time":"14:20","value":-9.2874},{"time":"14:21","value":-9.5257},{"time":"14:22","value":-9.6271},{"time":"14:23","value":-9.7792},{"time":"14:24","value":-9.8193},{"time":"14:25","value":-9.9062},{"time":"14:26","value":-9.9322},{"time":"14:27","value":-9.9318},{"time":"14:28","value":-9.9558},{"time":"14:29","value":-9.9568},{"time":"14:30","value":-10.0231},{"time":"14:31","value":-10.0375}],"stale":false},{"order":23,"label":"煤炭","board_name":"煤炭","board_type":"industry","board_type_cn":"行业板块","market":90,"trade_date":"2026-07-15","trade_time":"2026-07-15 14:31","minute":"14:31","value":-1.6031,"super_large":-0.9756,"large":-0.6275,"medium":-1.3385,"small":2.9395,"history":[{"time":"13:52","value":-2.0451},{"time":"13:53","value":-2.0349},{"time":"13:54","value":-1.9812},{"time":"13:55","value":-1.9835},{"time":"13:56","value":-1.9657},{"time":"13:57","value":-1.9523},{"time":"13:58","value":-1.9376},{"time":"13:59","value":-1.9372},{"time":"14:00","value":-1.9253},{"time":"14:01","value":-1.867},{"time":"14:02","value":-1.8905},{"time":"14:03","value":-1.9188},{"time":"14:04","value":-1.9504},{"time":"14:05","value":-1.961},{"time":"14:06","value":-2.0007},{"time":"14:07","value":-2.0008},{"time":"14:08","value":-2.0078},{"time":"14:09","value":-1.9525},{"time":"14:10","value":-1.8917},{"time":"14:11","value":-1.8508},{"time":"14:12","value":-1.8477},{"time":"14:13","value":-1.806},{"time":"14:14","value":-1.8069},{"time":"14:15","value":-1.773},{"time":"14:16","value":-1.7342},{"time":"14:17","value":-1.7223},{"time":"14:18","value":-1.7354},{"time":"14:19","value":-1.7613},{"time":"14:20","value":-1.7658},{"time":"14:21","value":-1.7905},{"time":"14:22","value":-1.8301},{"time":"14:23","value":-1.8572},{"time":"14:24","value":-1.8226},{"time":"14:25","value":-1.7818},{"time":"14:26","value":-1.7243},{"time":"14:27","value":-1.7153},{"time":"14:28","value":-1.6686},{"time":"14:29","value":-1.6602},{"time":"14:30","value":-1.7007},{"time":"14:31","value":-1.6031}],"stale":false},{"order":24,"label":"稀土","board_name":"稀土","board_type":"industry","board_type_cn":"行业板块","market":90,"trade_date":"2026-07-15","trade_time":"2026-07-15 14:31","minute":"14:31","value":-1.1084,"super_large":-0.1006,"large":-1.0078,"medium":1.3038,"small":-0.1951,"history":[{"time":"13:52","value":-0.5939},{"time":"13:53","value":-0.6085},{"time":"13:54","value":-0.5899},{"time":"13:55","value":-0.6109},{"time":"13:56","value":-0.6019},{"time":"13:57","value":-0.6038},{"time":"13:58","value":-0.6312},{"time":"13:59","value":-0.6451},{"time":"14:00","value":-0.6617},{"time":"14:01","value":-0.6876},{"time":"14:02","value":-0.7294},{"time":"14:03","value":-0.7139},{"time":"14:04","value":-0.7169},{"time":"14:05","value":-0.7153},{"time":"14:06","value":-0.7241},{"time":"14:07","value":-0.7198},{"time":"14:08","value":-0.7206},{"time":"14:09","value":-0.7174},{"time":"14:10","value":-0.7622},{"time":"14:11","value":-0.7845},{"time":"14:12","value":-0.8322},{"time":"14:13","value":-0.8477},{"time":"14:14","value":-0.8832},{"time":"14:15","value":-0.901},{"time":"14:16","value":-0.9098},{"time":"14:17","value":-0.9087},{"time":"14:18","value":-0.9079},{"time":"14:19","value":-0.9304},{"time":"14:20","value":-0.8961},{"time":"14:21","value":-0.9815},{"time":"14:22","value":-1.0101},{"time":"14:23","value":-1.073},{"time":"14:24","value":-1.067},{"time":"14:25","value":-1.0945},{"time":"14:26","value":-1.0857},{"time":"14:27","value":-1.0847},{"time":"14:28","value":-1.0882},{"time":"14:29","value":-1.0601},{"time":"14:30","value":-1.0943},{"time":"14:31","value":-1.1084}],"stale":false},{"order":25,"label":"畜牧","board_name":"畜牧养殖","board_type":"industry","board_type_cn":"行业板块","market":90,"trade_date":"2026-07-15","trade_time":"2026-07-15 14:31","minute":"14:31","value":2.0132,"super_large":0.3299,"large":1.6832,"medium":-1.0512,"small":-0.962,"history":[{"time":"13:52","value":2.2525},{"time":"13:53","value":2.2556},{"time":"13:54","value":2.2599},{"time":"13:55","value":2.2282},{"time":"13:56","value":2.2384},{"time":"13:57","value":2.2325},{"time":"13:58","value":2.2104},{"time":"13:59","value":2.1731},{"time":"14:00","value":2.1481},{"time":"14:01","value":2.151},{"time":"14:02","value":2.1412},{"time":"14:03","value":2.1446},{"time":"14:04","value":2.1944},{"time":"14:05","value":2.211},{"time":"14:06","value":2.2228},{"time":"14:07","value":2.2332},{"time":"14:08","value":2.2185},{"time":"14:09","value":2.2118},{"time":"14:10","value":2.2097},{"time":"14:11","value":2.1853},{"time":"14:12","value":2.1557},{"time":"14:13","value":2.125},{"time":"14:14","value":2.1128},{"time":"14:15","value":2.1007},{"time":"14:16","value":2.0928},{"time":"14:17","value":2.1061},{"time":"14:18","value":2.1122},{"time":"14:19","value":2.1338},{"time":"14:20","value":2.11},{"time":"14:21","value":2.1234},{"time":"14:22","value":2.1232},{"time":"14:23","value":2.112},{"time":"14:24","value":2.109},{"time":"14:25","value":2.0893},{"time":"14:26","value":2.0315},{"time":"14:27","value":2.0368},{"time":"14:28","value":2.0092},{"time":"14:29","value":2.017},{"time":"14:30","value":2.0408},{"time":"14:31","value":2.0132}],"stale":false},{"order":26,"label":"电力","board_name":"电力","board_type":"industry","board_type_cn":"行业板块","market":90,"trade_date":"2026-07-15","trade_time":"2026-07-15 14:31","minute":"14:31","value":-9.0138,"super_large":-2.9288,"large":-6.085,"medium":-1.4898,"small":10.5011,"history":[{"time":"13:52","value":-8.9902},{"time":"13:53","value":-8.9588},{"time":"13:54","value":-8.9747},{"time":"13:55","value":-8.9813},{"time":"13:56","value":-8.9607},{"time":"13:57","value":-8.9641},{"time":"13:58","value":-8.9707},{"time":"13:59","value":-9.0767},{"time":"14:00","value":-9.2032},{"time":"14:01","value":-9.3844},{"time":"14:02","value":-9.5696},{"time":"14:03","value":-9.6903},{"time":"14:04","value":-9.6962},{"time":"14:05","value":-9.6693},{"time":"14:06","value":-9.7332},{"time":"14:07","value":-9.7935},{"time":"14:08","value":-9.7686},{"time":"14:09","value":-9.7192},{"time":"14:10","value":-9.7382},{"time":"14:11","value":-9.7734},{"time":"14:12","value":-9.7697},{"time":"14:13","value":-9.7046},{"time":"14:14","value":-9.6723},{"time":"14:15","value":-9.6294},{"time":"14:16","value":-9.6093},{"time":"14:17","value":-9.5274},{"time":"14:18","value":-9.4986},{"time":"14:19","value":-9.4649},{"time":"14:20","value":-9.5777},{"time":"14:21","value":-9.6978},{"time":"14:22","value":-9.7735},{"time":"14:23","value":-9.7077},{"time":"14:24","value":-9.7008},{"time":"14:25","value":-9.5617},{"time":"14:26","value":-9.3673},{"time":"14:27","value":-9.2217},{"time":"14:28","value":-9.218},{"time":"14:29","value":-9.193},{"time":"14:30","value":-9.0709},{"time":"14:31","value":-9.0138}],"stale":false},{"order":27,"label":"保险","board_name":"保险Ⅱ","board_type":"industry","board_type_cn":"行业板块","market":90,"trade_date":"2026-07-15","trade_time":"2026-07-15 14:31","minute":"14:31","value":7.1177,"super_large":2.5102,"large":4.6075,"medium":-0.1808,"small":-6.9374,"history":[{"time":"13:52","value":7.1792},{"time":"13:53","value":7.1063},{"time":"13:54","value":7.0826},{"time":"13:55","value":7.1275},{"time":"13:56","value":7.1304},{"time":"13:57","value":7.1183},{"time":"13:58","value":7.074},{"time":"13:59","value":7.0401},{"time":"14:00","value":7.0216},{"time":"14:01","value":6.9622},{"time":"14:02","value":6.9461},{"time":"14:03","value":6.9509},{"time":"14:04","value":7.0193},{"time":"14:05","value":7.2237},{"time":"14:06","value":7.2625},{"time":"14:07","value":7.2686},{"time":"14:08","value":7.3061},{"time":"14:09","value":7.3251},{"time":"14:10","value":7.3608},{"time":"14:11","value":7.357},{"time":"14:12","value":7.3435},{"time":"14:13","value":7.3068},{"time":"14:14","value":7.3482},{"time":"14:15","value":7.3565},{"time":"14:16","value":7.3104},{"time":"14:17","value":7.2715},{"time":"14:18","value":7.2732},{"time":"14:19","value":7.2793},{"time":"14:20","value":7.3438},{"time":"14:21","value":7.3377},{"time":"14:22","value":7.3402},{"time":"14:23","value":7.2402},{"time":"14:24","value":7.1671},{"time":"14:25","value":7.1071},{"time":"14:26","value":7.0404},{"time":"14:27","value":7.0204},{"time":"14:28","value":7.0506},{"time":"14:29","value":7.0501},{"time":"14:30","value":7.1325},{"time":"14:31","value":7.1177}],"stale":false},{"order":28,"label":"游戏","board_name":"游戏Ⅱ","board_type":"industry","board_type_cn":"行业板块","market":90,"trade_date":"2026-07-15","trade_time":"2026-07-15 14:31","minute":"14:31","value":16.6963,"super_large":13.0419,"large":3.6544,"medium":-9.0994,"small":-7.5969,"history":[{"time":"13:52","value":16.9409},{"time":"13:53","value":16.9223},{"time":"13:54","value":16.9219},{"time":"13:55","value":16.9211},{"time":"13:56","value":16.9225},{"time":"13:57","value":16.8933},{"time":"13:58","value":16.8773},{"time":"13:59","value":16.8633},{"time":"14:00","value":16.8907},{"time":"14:01","value":16.9018},{"time":"14:02","value":16.8977},{"time":"14:03","value":16.8553},{"time":"14:04","value":16.876},{"time":"14:05","value":16.8839},{"time":"14:06","value":16.8938},{"time":"14:07","value":16.8674},{"time":"14:08","value":16.8496},{"time":"14:09","value":16.847},{"time":"14:10","value":16.8222},{"time":"14:11","value":16.8318},{"time":"14:12","value":16.8461},{"time":"14:13","value":16.8327},{"time":"14:14","value":16.8266},{"time":"14:15","value":16.8331},{"time":"14:16","value":16.845},{"time":"14:17","value":16.8402},{"time":"14:18","value":16.8598},{"time":"14:19","value":16.8831},{"time":"14:20","value":16.8954},{"time":"14:21","value":16.8624},{"time":"14:22","value":16.8495},{"time":"14:23","value":16.8582},{"time":"14:24","value":16.7008},{"time":"14:25","value":16.7217},{"time":"14:26","value":16.7081},{"time":"14:27","value":16.7295},{"time":"14:28","value":16.7074},{"time":"14:29","value":16.6975},{"time":"14:30","value":16.7101},{"time":"14:31","value":16.6963}],"stale":false},{"order":29,"label":"储能","board_name":"储能概念","board_type":"concept","board_type_cn":"概念板块","market":90,"trade_date":"2026-07-15","trade_time":"2026-07-15 14:31","minute":"14:31","value":-19.695,"super_large":-11.0591,"large":-8.6359,"medium":-12.9023,"small":32.1478,"history":[{"time":"13:52","value":-8.7587},{"time":"13:53","value":-9.0535},{"time":"13:54","value":-9.3111},{"time":"13:55","value":-9.5388},{"time":"13:56","value":-9.5109},{"time":"13:57","value":-9.487},{"time":"13:58","value":-9.6398},{"time":"13:59","value":-9.9104},{"time":"14:00","value":-10.6096},{"time":"14:01","value":-10.8733},{"time":"14:02","value":-11.9529},{"time":"14:03","value":-12.4205},{"time":"14:04","value":-12.4332},{"time":"14:05","value":-12.8565},{"time":"14:06","value":-13.2348},{"time":"14:07","value":-13.4115},{"time":"14:08","value":-13.6336},{"time":"14:09","value":-14.1039},{"time":"14:10","value":-14.732},{"time":"14:11","value":-15.6255},{"time":"14:12","value":-16.2261},{"time":"14:13","value":-16.3664},{"time":"14:14","value":-16.7617},{"time":"14:15","value":-16.691},{"time":"14:16","value":-16.6977},{"time":"14:17","value":-16.7423},{"time":"14:18","value":-16.6096},{"time":"14:19","value":-16.6093},{"time":"14:20","value":-16.7851},{"time":"14:21","value":-17.7013},{"time":"14:22","value":-18.3484},{"time":"14:23","value":-18.9805},{"time":"14:24","value":-19.2778},{"time":"14:25","value":-19.6175},{"time":"14:26","value":-20.0002},{"time":"14:27","value":-20.0862},{"time":"14:28","value":-20.1959},{"time":"14:29","value":-20.0511},{"time":"14:30","value":-19.6902},{"time":"14:31","value":-19.695}],"stale":false},{"order":30,"label":"军工","board_name":"军工","board_type":"industry","board_type_cn":"行业板块","market":90,"trade_date":"2026-07-15","trade_time":"2026-07-15 14:31","minute":"14:31","value":-51.7811,"super_large":-30.6355,"large":-21.1457,"medium":5.0476,"small":46.3226,"history":[{"time":"13:52","value":-40.7005},{"time":"13:53","value":-40.834},{"time":"13:54","value":-40.9967},{"time":"13:55","value":-41.2879},{"time":"13:56","value":-41.2802},{"time":"13:57","value":-41.4328},{"time":"13:58","value":-41.8273},{"time":"13:59","value":-42.2774},{"time":"14:00","value":-42.8674},{"time":"14:01","value":-42.9447},{"time":"14:02","value":-43.6298},{"time":"14:03","value":-44.0573},{"time":"14:04","value":-44.2829},{"time":"14:05","value":-44.8898},{"time":"14:06","value":-45.3688},{"time":"14:07","value":-45.8096},{"time":"14:08","value":-46.0328},{"time":"14:09","value":-46.2455},{"time":"14:10","value":-46.8238},{"time":"14:11","value":-47.3715},{"time":"14:12","value":-47.818},{"time":"14:13","value":-47.9663},{"time":"14:14","value":-48.4835},{"time":"14:15","value":-48.5002},{"time":"14:16","value":-48.4273},{"time":"14:17","value":-48.6915},{"time":"14:18","value":-48.641},{"time":"14:19","value":-48.7214},{"time":"14:20","value":-48.802},{"time":"14:21","value":-49.0421},{"time":"14:22","value":-49.3419},{"time":"14:23","value":-50.0163},{"time":"14:24","value":-50.3834},{"time":"14:25","value":-50.8852},{"time":"14:26","value":-51.3106},{"time":"14:27","value":-51.3844},{"time":"14:28","value":-51.2357},{"time":"14:29","value":-51.2636},{"time":"14:30","value":-51.5459},{"time":"14:31","value":-51.7811}],"stale":false},{"order":31,"label":"消费电子","board_name":"消费电子","board_type":"industry","board_type_cn":"行业板块","market":90,"trade_date":"2026-07-15","trade_time":"2026-07-15 14:31","minute":"14:31","value":-27.434,"super_large":-18.0248,"large":-9.4092,"medium":2.0111,"small":25.2298,"history":[{"time":"13:52","value":-18.6982},{"time":"13:53","value":-18.8082},{"time":"13:54","value":-18.9171},{"time":"13:55","value":-19.0565},{"time":"13:56","value":-19.1341},{"time":"13:57","value":-19.1757},{"time":"13:58","value":-19.2542},{"time":"13:59","value":-19.555},{"time":"14:00","value":-19.8091},{"time":"14:01","value":-19.9534},{"time":"14:02","value":-20.302},{"time":"14:03","value":-20.6024},{"time":"14:04","value":-20.6673},{"time":"14:05","value":-20.7232},{"time":"14:06","value":-20.8038},{"time":"14:07","value":-21.1154},{"time":"14:08","value":-21.3496},{"time":"14:09","value":-21.5169},{"time":"14:10","value":-21.6816},{"time":"14:11","value":-21.8913},{"time":"14:12","value":-22.2613},{"time":"14:13","value":-22.3402},{"time":"14:14","value":-22.5845},{"time":"14:15","value":-22.6961},{"time":"14:16","value":-22.8369},{"time":"14:17","value":-23.0138},{"time":"14:18","value":-23.1004},{"time":"14:19","value":-23.2811},{"time":"14:20","value":-23.6129},{"time":"14:21","value":-24.5477},{"time":"14:22","value":-25.241},{"time":"14:23","value":-25.4567},{"time":"14:24","value":-25.7561},{"time":"14:25","value":-26.2288},{"time":"14:26","value":-26.5985},{"time":"14:27","value":-26.7165},{"time":"14:28","value":-26.8562},{"time":"14:29","value":-27.0576},{"time":"14:30","value":-27.3361},{"time":"14:31","value":-27.434}],"stale":false},{"order":32,"label":"云计算","board_name":"云计算","board_type":"concept","board_type_cn":"概念板块","market":90,"trade_date":"2026-07-15","trade_time":"2026-07-15 14:31","minute":"14:31","value":-28.3648,"super_large":-22.3322,"large":-6.0326,"medium":14.0083,"small":14.2561,"history":[{"time":"13:52","value":-21.571},{"time":"13:53","value":-21.4697},{"time":"13:54","value":-21.4605},{"time":"13:55","value":-21.6143},{"time":"13:56","value":-21.4874},{"time":"13:57","value":-21.5873},{"time":"13:58","value":-21.9311},{"time":"13:59","value":-22.3261},{"time":"14:00","value":-22.6192},{"time":"14:01","value":-22.6076},{"time":"14:02","value":-22.962},{"time":"14:03","value":-23.2178},{"time":"14:04","value":-23.0498},{"time":"14:05","value":-23.2121},{"time":"14:06","value":-23.3652},{"time":"14:07","value":-23.5804},{"time":"14:08","value":-23.7887},{"time":"14:09","value":-23.8921},{"time":"14:10","value":-24.1225},{"time":"14:11","value":-24.2607},{"time":"14:12","value":-24.3914},{"time":"14:13","value":-24.3106},{"time":"14:14","value":-24.4112},{"time":"14:15","value":-24.3407},{"time":"14:16","value":-24.3344},{"time":"14:17","value":-24.5297},{"time":"14:18","value":-24.4894},{"time":"14:19","value":-24.8122},{"time":"14:20","value":-24.9232},{"time":"14:21","value":-25.5862},{"time":"14:22","value":-25.9678},{"time":"14:23","value":-26.6416},{"time":"14:24","value":-26.9746},{"time":"14:25","value":-27.4133},{"time":"14:26","value":-27.8593},{"time":"14:27","value":-27.78},{"time":"14:28","value":-27.7439},{"time":"14:29","value":-27.8984},{"time":"14:30","value":-28.1962},{"time":"14:31","value":-28.3648}],"stale":false},{"order":33,"label":"国产芯片","board_name":"国产芯片","board_type":"concept","board_type_cn":"概念板块","market":90,"trade_date":"2026-07-15","trade_time":"2026-07-15 14:31","minute":"14:31","value":-319.9502,"super_large":-235.4545,"large":-84.4958,"medium":124.9123,"small":194.9825,"history":[{"time":"13:52","value":-271.9618},{"time":"13:53","value":-272.4947},{"time":"13:54","value":-272.8133},{"time":"13:55","value":-273.5093},{"time":"13:56","value":-273.4686},{"time":"13:57","value":-273.5163},{"time":"13:58","value":-274.2151},{"time":"13:59","value":-275.3435},{"time":"14:00","value":-276.7001},{"time":"14:01","value":-277.704},{"time":"14:02","value":-280.7668},{"time":"14:03","value":-282.1199},{"time":"14:04","value":-283.0101},{"time":"14:05","value":-284.6123},{"time":"14:06","value":-286.2424},{"time":"14:07","value":-287.417},{"time":"14:08","value":-288.5156},{"time":"14:09","value":-289.8616},{"time":"14:10","value":-291.7615},{"time":"14:11","value":-293.6632},{"time":"14:12","value":-295.904},{"time":"14:13","value":-296.7742},{"time":"14:14","value":-298.1746},{"time":"14:15","value":-298.6699},{"time":"14:16","value":-299.0311},{"time":"14:17","value":-299.8772},{"time":"14:18","value":-299.7443},{"time":"14:19","value":-300.3372},{"time":"14:20","value":-301.606},{"time":"14:21","value":-303.6583},{"time":"14:22","value":-305.9985},{"time":"14:23","value":-308.6859},{"time":"14:24","value":-310.7648},{"time":"14:25","value":-313.5405},{"time":"14:26","value":-315.3745},{"time":"14:27","value":-315.9095},{"time":"14:28","value":-316.4864},{"time":"14:29","value":-317.2444},{"time":"14:30","value":-318.6569},{"time":"14:31","value":-319.9502}],"stale":false}],"errors":[],"disclaimer":"仅作数据可视化展示，不构成投资建议。","publisher":{"name":"shuige-private-public-publisher","cadence_seconds":60}}
