{"ok":true,"brand":"水哥养基","metric":"累计主力净额","unit":"亿元","source":"公开板块分钟资金流","trade_date":"2026-07-23","latest_time":"2026-07-23 09:38","updated_at":"2026-07-23T09:37:14+08:00","refresh_seconds":60,"market":{"code":"live","label":"交易中"},"summary":{"inflow_total":7.89,"outflow_total":-165.72,"leader":"MLCC","leader_value":7.0491,"laggard":"国产芯片","laggard_value":-28.0087},"sectors":[{"order":1,"label":"半导体","board_name":"半导体","board_type":"industry","board_type_cn":"行业板块","market":90,"trade_date":"2026-07-23","trade_time":"2026-07-23 09:38","minute":"09:38","value":-21.9377,"super_large":-15.4235,"large":-6.5142,"medium":11.5329,"small":10.3932,"history":[{"time":"09:31","value":-1.1407},{"time":"09:32","value":-4.2566},{"time":"09:33","value":-7.3297},{"time":"09:34","value":-12.1921},{"time":"09:35","value":-15.5596},{"time":"09:36","value":-19.2577},{"time":"09:37","value":-21.28},{"time":"09:38","value":-21.9377}],"stale":false},{"order":2,"label":"存储芯片","board_name":"存储芯片","board_type":"concept","board_type_cn":"概念板块","market":90,"trade_date":"2026-07-23","trade_time":"2026-07-23 09:38","minute":"09:38","value":-16.6478,"super_large":-10.3224,"large":-6.3254,"medium":7.6062,"small":9.0404,"history":[{"time":"09:31","value":-0.596},{"time":"09:32","value":-3.5694},{"time":"09:33","value":-6.6689},{"time":"09:34","value":-10.8002},{"time":"09:35","value":-13.081},{"time":"09:36","value":-15.5306},{"time":"09:37","value":-16.2157},{"time":"09:38","value":-16.6478}],"stale":false},{"order":3,"label":"MLCC","board_name":"MLCC","board_type":"concept","board_type_cn":"概念板块","market":90,"trade_date":"2026-07-23","trade_time":"2026-07-23 09:38","minute":"09:38","value":7.0491,"super_large":8.1391,"large":-1.0899,"medium":-3.5734,"small":-3.4744,"history":[{"time":"09:31","value":1.2667},{"time":"09:32","value":1.4408},{"time":"09:33","value":1.1525},{"time":"09:34","value":3.5242},{"time":"09:35","value":5.0336},{"time":"09:36","value":5.8127},{"time":"09:37","value":6.6806},{"time":"09:38","value":7.0491}],"stale":false},{"order":4,"label":"固态电池","board_name":"固态电池","board_type":"concept","board_type_cn":"概念板块","market":90,"trade_date":"2026-07-23","trade_time":"2026-07-23 09:38","minute":"09:38","value":-2.3883,"super_large":-0.7786,"large":-1.6096,"medium":0.3048,"small":2.1133,"history":[{"time":"09:31","value":-0.2508},{"time":"09:32","value":-0.7953},{"time":"09:33","value":-2.1533},{"time":"09:34","value":-2.9555},{"time":"09:35","value":-2.8364},{"time":"09:36","value":-2.6445},{"time":"09:37","value":-2.4753},{"time":"09:38","value":-2.3883}],"stale":false},{"order":5,"label":"锂矿","board_name":"锂矿概念","board_type":"concept","board_type_cn":"概念板块","market":90,"trade_date":"2026-07-23","trade_time":"2026-07-23 09:38","minute":"09:38","value":-1.1246,"super_large":-0.9756,"large":-0.1489,"medium":0.6925,"small":0.4309,"history":[{"time":"09:31","value":-0.1909},{"time":"09:32","value":-0.0644},{"time":"09:33","value":-0.7434},{"time":"09:34","value":-0.9131},{"time":"09:35","value":-0.8114},{"time":"09:36","value":-1.1363},{"time":"09:37","value":-1.1584},{"time":"09:38","value":-1.1246}],"stale":false},{"order":6,"label":"白酒","board_name":"白酒","board_type":"concept","board_type_cn":"概念板块","market":90,"trade_date":"2026-07-23","trade_time":"2026-07-23 09:38","minute":"09:38","value":-1.5964,"super_large":-0.5692,"large":-1.0272,"medium":0.5864,"small":1.0093,"history":[{"time":"09:31","value":-0.3734},{"time":"09:32","value":-0.5617},{"time":"09:33","value":-0.5946},{"time":"09:34","value":-0.666},{"time":"09:35","value":-0.8968},{"time":"09:36","value":-1.129},{"time":"09:37","value":-1.5951},{"time":"09:38","value":-1.5964}],"stale":false},{"order":7,"label":"创新药","board_name":"创新药","board_type":"concept","board_type_cn":"概念板块","market":90,"trade_date":"2026-07-23","trade_time":"2026-07-23 09:38","minute":"09:38","value":-4.475,"super_large":-1.8607,"large":-2.6143,"medium":-0.4788,"small":4.8866,"history":[{"time":"09:31","value":-1.1031},{"time":"09:32","value":-1.2118},{"time":"09:33","value":-1.417},{"time":"09:34","value":-1.5665},{"time":"09:35","value":-2.513},{"time":"09:36","value":-3.1903},{"time":"09:37","value":-4.1576},{"time":"09:38","value":-4.475}],"stale":false},{"order":8,"label":"生物疫苗","board_name":"生物疫苗","board_type":"concept","board_type_cn":"概念板块","market":90,"trade_date":"2026-07-23","trade_time":"2026-07-23 09:38","minute":"09:38","value":-0.2928,"super_large":0.3752,"large":-0.6681,"medium":-0.744,"small":1.0341,"history":[{"time":"09:31","value":-0.0844},{"time":"09:32","value":-0.1496},{"time":"09:33","value":0.0797},{"time":"09:34","value":0.0493},{"time":"09:35","value":-0.0976},{"time":"09:36","value":-0.0571},{"time":"09:37","value":-0.2203},{"time":"09:38","value":-0.2928}],"stale":false},{"order":9,"label":"PCB","board_name":"PCB","board_type":"concept","board_type_cn":"概念板块","market":90,"trade_date":"2026-07-23","trade_time":"2026-07-23 09:38","minute":"09:38","value":-1.9664,"super_large":-1.2331,"large":-0.7333,"medium":0.4755,"small":1.3763,"history":[{"time":"09:31","value":0.9087},{"time":"09:32","value":-0.9504},{"time":"09:33","value":-3.0235},{"time":"09:34","value":-4.4509},{"time":"09:35","value":-4.0553},{"time":"09:36","value":-3.206},{"time":"09:37","value":-2.1264},{"time":"09:38","value":-1.9664}],"stale":false},{"order":10,"label":"黄金","board_name":"黄金概念","board_type":"concept","board_type_cn":"概念板块","market":90,"trade_date":"2026-07-23","trade_time":"2026-07-23 09:38","minute":"09:38","value":-3.1088,"super_large":-1.4332,"large":-1.6756,"medium":0.4509,"small":2.655,"history":[{"time":"09:31","value":-0.7044},{"time":"09:32","value":-1.2161},{"time":"09:33","value":-1.8027},{"time":"09:34","value":-2.2876},{"time":"09:35","value":-2.231},{"time":"09:36","value":-2.6144},{"time":"09:37","value":-2.9229},{"time":"09:38","value":-3.1088}],"stale":false},{"order":11,"label":"CPO","board_name":"CPO概念","board_type":"concept","board_type_cn":"概念板块","market":90,"trade_date":"2026-07-23","trade_time":"2026-07-23 09:38","minute":"09:38","value":-7.7926,"super_large":-4.87,"large":-2.9225,"medium":0.8768,"small":6.9479,"history":[{"time":"09:31","value":1.4422},{"time":"09:32","value":-1.9934},{"time":"09:33","value":-3.4308},{"time":"09:34","value":-5.632},{"time":"09:35","value":-7.2075},{"time":"09:36","value":-8.0501},{"time":"09:37","value":-7.8668},{"time":"09:38","value":-7.7926}],"stale":false},{"order":12,"label":"算力","board_name":"算力概念","board_type":"concept","board_type_cn":"概念板块","market":90,"trade_date":"2026-07-23","trade_time":"2026-07-23 09:38","minute":"09:38","value":-8.1099,"super_large":-3.2835,"large":-4.8264,"medium":-0.8975,"small":8.953,"history":[{"time":"09:31","value":1.7783},{"time":"09:32","value":-0.3756},{"time":"09:33","value":-3.5415},{"time":"09:34","value":-5.9497},{"time":"09:35","value":-8.0422},{"time":"09:36","value":-9.5695},{"time":"09:37","value":-8.4297},{"time":"09:38","value":-8.1099}],"stale":false},{"order":13,"label":"液冷","board_name":"液冷概念","board_type":"concept","board_type_cn":"概念板块","market":90,"trade_date":"2026-07-23","trade_time":"2026-07-23 09:38","minute":"09:38","value":-5.0799,"super_large":-6.8452,"large":1.7653,"medium":0.9184,"small":4.2113,"history":[{"time":"09:31","value":-0.4107},{"time":"09:32","value":-3.311},{"time":"09:33","value":-5.779},{"time":"09:34","value":-7.4944},{"time":"09:35","value":-7.8553},{"time":"09:36","value":-6.8172},{"time":"09:37","value":-5.4901},{"time":"09:38","value":-5.0799}],"stale":false},{"order":14,"label":"光伏","board_name":"光伏概念","board_type":"concept","board_type_cn":"概念板块","market":90,"trade_date":"2026-07-23","trade_time":"2026-07-23 09:38","minute":"09:38","value":-4.7815,"super_large":-0.4845,"large":-4.297,"medium":-3.1877,"small":7.9928,"history":[{"time":"09:31","value":-1.5373},{"time":"09:32","value":-1.6747},{"time":"09:33","value":-2.837},{"time":"09:34","value":-3.5232},{"time":"09:35","value":-4.4088},{"time":"09:36","value":-4.7379},{"time":"09:37","value":-4.8819},{"time":"09:38","value":-4.7815}],"stale":false},{"order":15,"label":"人形机器人","board_name":"人形机器人","board_type":"concept","board_type_cn":"概念板块","market":90,"trade_date":"2026-07-23","trade_time":"2026-07-23 09:38","minute":"09:38","value":-6.7292,"super_large":-3.9416,"large":-2.7876,"medium":2.5877,"small":4.1009,"history":[{"time":"09:31","value":-0.3839},{"time":"09:32","value":-2.3362},{"time":"09:33","value":-3.5981},{"time":"09:34","value":-5.4004},{"time":"09:35","value":-6.6118},{"time":"09:36","value":-6.6905},{"time":"09:37","value":-6.8115},{"time":"09:38","value":-6.7292}],"stale":false},{"order":16,"label":"AI应用","board_name":"AI应用","board_type":"concept","board_type_cn":"概念板块","market":90,"trade_date":"2026-07-23","trade_time":"2026-07-23 09:38","minute":"09:38","value":-8.0917,"super_large":-3.8532,"large":-4.2385,"medium":0.9514,"small":7.0496,"history":[{"time":"09:31","value":-2.1422},{"time":"09:32","value":-3.6317},{"time":"09:33","value":-4.8927},{"time":"09:34","value":-6.3036},{"time":"09:35","value":-6.992},{"time":"09:36","value":-7.3953},{"time":"09:37","value":-7.7727},{"time":"09:38","value":-8.0917}],"stale":false},{"order":17,"label":"新能源车","board_name":"新能源车","board_type":"concept","board_type_cn":"概念板块","market":90,"trade_date":"2026-07-23","trade_time":"2026-07-23 09:38","minute":"09:38","value":-5.9112,"super_large":-1.7837,"large":-4.1275,"medium":-1.4921,"small":7.2339,"history":[{"time":"09:31","value":-0.3626},{"time":"09:32","value":-2.4896},{"time":"09:33","value":-5.2659},{"time":"09:34","value":-7.1453},{"time":"09:35","value":-7.3405},{"time":"09:36","value":-6.3438},{"time":"09:37","value":-6.1037},{"time":"09:38","value":-5.9112}],"stale":false},{"order":18,"label":"商业航天","board_name":"商业航天","board_type":"concept","board_type_cn":"概念板块","market":90,"trade_date":"2026-07-23","trade_time":"2026-07-23 09:38","minute":"09:38","value":-2.4695,"super_large":-1.6611,"large":-0.8083,"medium":-0.2373,"small":2.6728,"history":[{"time":"09:31","value":-1.2561},{"time":"09:32","value":-2.4589},{"time":"09:33","value":-3.4881},{"time":"09:34","value":-4.6401},{"time":"09:35","value":-4.5957},{"time":"09:36","value":-3.8188},{"time":"09:37","value":-2.856},{"time":"09:38","value":-2.4695}],"stale":false},{"order":19,"label":"银行","board_name":"银行","board_type":"industry","board_type_cn":"行业板块","market":90,"trade_date":"2026-07-23","trade_time":"2026-07-23 09:38","minute":"09:38","value":-0.4134,"super_large":-0.1336,"large":-0.2798,"medium":-0.2654,"small":0.6744,"history":[{"time":"09:31","value":-0.3219},{"time":"09:32","value":-0.4322},{"time":"09:33","value":-0.4226},{"time":"09:34","value":-0.6279},{"time":"09:35","value":-0.3985},{"time":"09:36","value":-0.284},{"time":"09:37","value":-0.3849},{"time":"09:38","value":-0.4134}],"stale":false},{"order":20,"label":"证券","board_name":"证券","board_type":"industry","board_type_cn":"行业板块","market":90,"trade_date":"2026-07-23","trade_time":"2026-07-23 09:38","minute":"09:38","value":-0.9907,"super_large":-0.1783,"large":-0.8124,"medium":0.0676,"small":0.9076,"history":[{"time":"09:31","value":-0.3274},{"time":"09:32","value":-0.4652},{"time":"09:33","value":-0.3876},{"time":"09:34","value":-0.5527},{"time":"09:35","value":-0.7434},{"time":"09:36","value":-0.8416},{"time":"09:37","value":-0.961},{"time":"09:38","value":-0.9907}],"stale":false},{"order":21,"label":"有色金属","board_name":"有色金属","board_type":"industry","board_type_cn":"行业板块","market":90,"trade_date":"2026-07-23","trade_time":"2026-07-23 09:38","minute":"09:38","value":-3.8917,"super_large":-2.1129,"large":-1.7789,"medium":0.3197,"small":3.589,"history":[{"time":"09:31","value":-0.8764},{"time":"09:32","value":-2.0969},{"time":"09:33","value":-2.9647},{"time":"09:34","value":-3.4957},{"time":"09:35","value":-3.2345},{"time":"09:36","value":-3.5679},{"time":"09:37","value":-4.0912},{"time":"09:38","value":-3.8917}],"stale":false},{"order":22,"label":"细分化工","board_name":"细分化工","board_type":"index","board_type_cn":"指数","market":1,"trade_date":"2026-07-23","trade_time":"2026-07-23 09:38","minute":"09:38","value":-1.0095,"super_large":-0.0506,"large":-0.9589,"medium":-0.0014,"small":1.0103,"history":[{"time":"09:31","value":-0.0522},{"time":"09:32","value":-0.3287},{"time":"09:33","value":-0.4811},{"time":"09:34","value":-0.3609},{"time":"09:35","value":-0.4671},{"time":"09:36","value":-0.5844},{"time":"09:37","value":-0.9577},{"time":"09:38","value":-1.0095}],"stale":false},{"order":23,"label":"煤炭","board_name":"煤炭","board_type":"industry","board_type_cn":"行业板块","market":90,"trade_date":"2026-07-23","trade_time":"2026-07-23 09:38","minute":"09:38","value":-0.659,"super_large":0.1812,"large":-0.8402,"medium":-0.0296,"small":0.6882,"history":[{"time":"09:31","value":0.0099},{"time":"09:32","value":-0.0457},{"time":"09:33","value":-0.1846},{"time":"09:34","value":-0.1976},{"time":"09:35","value":-0.3206},{"time":"09:36","value":-0.4853},{"time":"09:37","value":-0.6289},{"time":"09:38","value":-0.659}],"stale":false},{"order":24,"label":"稀土","board_name":"稀土","board_type":"industry","board_type_cn":"行业板块","market":90,"trade_date":"2026-07-23","trade_time":"2026-07-23 09:38","minute":"09:38","value":-0.3612,"super_large":-0.0844,"large":-0.2768,"medium":0.022,"small":0.3392,"history":[{"time":"09:31","value":-0.0615},{"time":"09:32","value":-0.179},{"time":"09:33","value":-0.1677},{"time":"09:34","value":-0.2203},{"time":"09:35","value":-0.2791},{"time":"09:36","value":-0.2547},{"time":"09:37","value":-0.327},{"time":"09:38","value":-0.3612}],"stale":false},{"order":25,"label":"畜牧","board_name":"畜牧养殖","board_type":"industry","board_type_cn":"行业板块","market":90,"trade_date":"2026-07-23","trade_time":"2026-07-23 09:38","minute":"09:38","value":-0.4637,"super_large":0.005,"large":-0.4687,"medium":0.096,"small":0.3678,"history":[{"time":"09:31","value":-0.1787},{"time":"09:32","value":-0.1338},{"time":"09:33","value":-0.1531},{"time":"09:34","value":-0.1748},{"time":"09:35","value":-0.3012},{"time":"09:36","value":-0.3631},{"time":"09:37","value":-0.4505},{"time":"09:38","value":-0.4637}],"stale":false},{"order":26,"label":"电力","board_name":"电力","board_type":"industry","board_type_cn":"行业板块","market":90,"trade_date":"2026-07-23","trade_time":"2026-07-23 09:38","minute":"09:38","value":-10.2313,"super_large":-5.1172,"large":-5.1142,"medium":-0.1057,"small":10.3357,"history":[{"time":"09:31","value":-1.9375},{"time":"09:32","value":-1.5976},{"time":"09:33","value":-3.2831},{"time":"09:34","value":-4.176},{"time":"09:35","value":-5.93},{"time":"09:36","value":-7.6042},{"time":"09:37","value":-9.9528},{"time":"09:38","value":-10.2313}],"stale":false},{"order":27,"label":"保险","board_name":"保险Ⅱ","board_type":"industry","board_type_cn":"行业板块","market":90,"trade_date":"2026-07-23","trade_time":"2026-07-23 09:38","minute":"09:38","value":-0.1608,"super_large":0.0631,"large":-0.2238,"medium":0.0324,"small":0.1286,"history":[{"time":"09:31","value":0.0542},{"time":"09:32","value":-0.0465},{"time":"09:33","value":-0.0095},{"time":"09:34","value":0.0457},{"time":"09:35","value":0.0569},{"time":"09:36","value":-0.0091},{"time":"09:37","value":-0.1051},{"time":"09:38","value":-0.1608}],"stale":false},{"order":28,"label":"游戏","board_name":"游戏Ⅱ","board_type":"industry","board_type_cn":"行业板块","market":90,"trade_date":"2026-07-23","trade_time":"2026-07-23 09:38","minute":"09:38","value":-2.0343,"super_large":-0.7319,"large":-1.3023,"medium":-0.0794,"small":2.1123,"history":[{"time":"09:31","value":-0.5274},{"time":"09:32","value":-0.7878},{"time":"09:33","value":-1.0622},{"time":"09:34","value":-1.3096},{"time":"09:35","value":-1.6596},{"time":"09:36","value":-1.8022},{"time":"09:37","value":-1.997},{"time":"09:38","value":-2.0343}],"stale":false},{"order":29,"label":"储能","board_name":"储能概念","board_type":"concept","board_type_cn":"概念板块","market":90,"trade_date":"2026-07-23","trade_time":"2026-07-23 09:38","minute":"09:38","value":-2.5186,"super_large":-1.211,"large":-1.3076,"medium":-2.2233,"small":4.7195,"history":[{"time":"09:31","value":-1.4743},{"time":"09:32","value":-1.0782},{"time":"09:33","value":-1.7053},{"time":"09:34","value":-2.3563},{"time":"09:35","value":-3.5331},{"time":"09:36","value":-2.7817},{"time":"09:37","value":-2.623},{"time":"09:38","value":-2.5186}],"stale":false},{"order":30,"label":"军工","board_name":"军工","board_type":"industry","board_type_cn":"行业板块","market":90,"trade_date":"2026-07-23","trade_time":"2026-07-23 09:38","minute":"09:38","value":-3.2082,"super_large":-1.4371,"large":-1.7712,"medium":-1.0517,"small":4.2724,"history":[{"time":"09:31","value":-0.9989},{"time":"09:32","value":-2.0236},{"time":"09:33","value":-3.117},{"time":"09:34","value":-3.638},{"time":"09:35","value":-4.2575},{"time":"09:36","value":-3.7299},{"time":"09:37","value":-3.3724},{"time":"09:38","value":-3.2082}],"stale":false},{"order":31,"label":"消费电子","board_name":"消费电子","board_type":"industry","board_type_cn":"行业板块","market":90,"trade_date":"2026-07-23","trade_time":"2026-07-23 09:38","minute":"09:38","value":0.8423,"super_large":1.0401,"large":-0.1979,"medium":-0.8497,"small":-0.0198,"history":[{"time":"09:31","value":-0.5887},{"time":"09:32","value":-0.7873},{"time":"09:33","value":-1.47},{"time":"09:34","value":-1.7964},{"time":"09:35","value":-1.7555},{"time":"09:36","value":-1.0561},{"time":"09:37","value":0.5076},{"time":"09:38","value":0.8423}],"stale":false},{"order":32,"label":"云计算","board_name":"云计算","board_type":"concept","board_type_cn":"概念板块","market":90,"trade_date":"2026-07-23","trade_time":"2026-07-23 09:38","minute":"09:38","value":-9.2635,"super_large":-6.1837,"large":-3.0798,"medium":1.3844,"small":7.8031,"history":[{"time":"09:31","value":-1.2998},{"time":"09:32","value":-3.6031},{"time":"09:33","value":-6.2449},{"time":"09:34","value":-8.1928},{"time":"09:35","value":-9.6894},{"time":"09:36","value":-10.7386},{"time":"09:37","value":-9.4736},{"time":"09:38","value":-9.2635}],"stale":false},{"order":33,"label":"国产芯片","board_name":"国产芯片","board_type":"concept","board_type_cn":"概念板块","market":90,"trade_date":"2026-07-23","trade_time":"2026-07-23 09:38","minute":"09:38","value":-28.0087,"super_large":-18.1317,"large":-9.877,"medium":8.7749,"small":19.1871,"history":[{"time":"09:31","value":-2.21},{"time":"09:32","value":-7.317},{"time":"09:33","value":-12.8537},{"time":"09:34","value":-18.2162},{"time":"09:35","value":-22.0165},{"time":"09:36","value":-25.3954},{"time":"09:37","value":-27.3113},{"time":"09:38","value":-28.0087}],"stale":false}],"errors":[],"disclaimer":"仅作数据可视化展示，不构成投资建议。","publisher":{"name":"shuige-private-public-publisher","cadence_seconds":60}}
